pyProcessingPipeline/__init__.py
pyProcessingPipeline/exceptions.py
pyProcessingPipeline/processing_run.py
pyProcessingPipeline/types.py
pyProcessingPipeline/util.py
pyProcessingPipeline/io/__init__.py
pyProcessingPipeline/io/_database.py
pyProcessingPipeline/io/_importer.py
pyProcessingPipeline/io/_records.py
pyProcessingPipeline/io/_timeseries.py
pyProcessingPipeline/io/exceptions.py
pyProcessingPipeline/steps/__init__.py
pyProcessingPipeline/steps/_base.py
pyProcessingPipeline/steps/_step_identifiers.py
pyProcessingPipeline/steps/_step_lookup.py
pyProcessingPipeline/steps/classification/__init__.py
pyProcessingPipeline/steps/classification/knn.py
pyProcessingPipeline/steps/feature_extraction/__init__.py
pyProcessingPipeline/steps/feature_extraction/spectrum.py
pyProcessingPipeline/steps/filters/__init__.py
pyProcessingPipeline/steps/filters/bessel.py
pyProcessingPipeline/steps/filters/butterworth.py
pyProcessingPipeline/steps/filters/chebyshev.py
pyProcessingPipeline/steps/filters/fir.py
pyProcessingPipeline/steps/misc/__init__.py
pyProcessingPipeline/steps/misc/cut.py
pyProcessingPipeline/steps/misc/labels.py
pyProcessingPipeline/steps/misc/split.py
pyProcessingPipeline/steps/misc/statistics.py
pyProcessingPipeline/steps/misc/unite.py
pyProcessingPipeline/steps/preprocessing/__init__.py
pyProcessingPipeline/steps/preprocessing/averaging.py
pyProcessingPipeline/steps/preprocessing/baseline_correction.py
pyProcessingPipeline/steps/preprocessing/normalization.py
pyProcessingPipeline-0.3.1.dist-info/METADATA
pyProcessingPipeline-0.3.1.dist-info/WHEEL
pyProcessingPipeline-0.3.1.dist-info/top_level.txt
pyProcessingPipeline-0.3.1.dist-info/RECORD
