Metadata-Version: 2.1
Name: pyProcessingPipeline
Version: 0.3.1
Summary: Package for defining processing pipelines.
Author-email: Christian Teichert <christian.teichert@lse.thm.de>, Urs Hackstein <urs.hackstein@lse.thm.de>
Project-URL: homepage, https://gitlab.com/agbernhard.lse.thm/agb_public/pyProcessingPipeline
Keywords: processing,signal,physiological signal
Classifier: Development Status :: 2 - Pre-Alpha
Classifier: Operating System :: OS Independent
Classifier: Intended Audience :: Science/Research
Classifier: Intended Audience :: Developers
Classifier: Programming Language :: Python :: 3 :: Only
Classifier: Programming Language :: Python :: 3
Classifier: Programming Language :: Python :: 3.10
Classifier: Programming Language :: Python :: 3.11
Classifier: Programming Language :: Python :: 3.12
Classifier: Programming Language :: Python
Classifier: Typing :: Typed
Requires-Python: >=3.10
Requires-Dist: numpy ==1.*
Requires-Dist: scipy ==1.*
Requires-Dist: wfdb ==4.*
Requires-Dist: scikit-learn ==1.*
Requires-Dist: emd ==0.7.*
Requires-Dist: mysql-connector-python ==9.*
Requires-Dist: matplotlib ==3.*
Provides-Extra: build
Requires-Dist: twine ==5.* ; extra == 'build'
Provides-Extra: dev
Requires-Dist: pip-tools ==7.* ; extra == 'dev'
Requires-Dist: black ==24.* ; extra == 'dev'
Requires-Dist: mypy ==1.* ; extra == 'dev'
Requires-Dist: ruff ==0.7.* ; extra == 'dev'
Requires-Dist: bandit ==1.* ; extra == 'dev'
Requires-Dist: commitizen ==3.* ; extra == 'dev'
Provides-Extra: dev-jupyter
Requires-Dist: ipykernel ==6.* ; extra == 'dev-jupyter'
Requires-Dist: plotly ==5.* ; extra == 'dev-jupyter'
Requires-Dist: nbformat ==5.* ; extra == 'dev-jupyter'
Requires-Dist: pandas ==2.* ; extra == 'dev-jupyter'
Provides-Extra: docs
Requires-Dist: sphinx ==8.* ; extra == 'docs'
Requires-Dist: sphinx-rtd-theme ==3.* ; extra == 'docs'
Provides-Extra: testing
Requires-Dist: coverage ==7.* ; extra == 'testing'
Requires-Dist: pytest ==8.* ; extra == 'testing'
